noseiquela_orm/__init__.py
noseiquela_orm/client.py
noseiquela_orm/entity.py
noseiquela_orm/key.py
noseiquela_orm/properties.py
noseiquela_orm/query.py
noseiquela_orm/utils/__init__.py
noseiquela_orm/utils/case_style.py
noseiquela_orm-0.0.8.dev1.dist-info/LICENSE
noseiquela_orm-0.0.8.dev1.dist-info/METADATA
noseiquela_orm-0.0.8.dev1.dist-info/WHEEL
noseiquela_orm-0.0.8.dev1.dist-info/top_level.txt
noseiquela_orm-0.0.8.dev1.dist-info/RECORD
