Metadata-Version: 2.1
Name: noseiquela-orm
Version: 0.0.8.dev1
Summary: Small and expressive ORM to interact with Google Datastore inspired by Django, Mongo-Engine and Peewee
Home-page: https://github.com/exageraldo/noseiquela-orm
Author: Geraldo Castro
Author-email: victormatheuscastro@gmail.com
License: BSD-3-Clause
Project-URL: Bug Tracker, https://github.com/exageraldo/noseiquela-orm/issues
Platform: UNKNOWN
Classifier: Development Status :: 4 - Beta
Classifier: Intended Audience :: Developers
Classifier: License :: OSI Approved :: BSD License
Classifier: Operating System :: OS Independent
Classifier: Programming Language :: Python
Classifier: Programming Language :: Python :: 3
Classifier: Programming Language :: Python :: 3.8
Classifier: Programming Language :: Python :: 3.9
Classifier: Programming Language :: Python :: 3.10
Classifier: Topic :: Database :: Front-Ends
Classifier: Topic :: Software Development :: Libraries :: Python Modules
Requires-Python: >=3.8
Requires-Dist: python-dateutil (~=2.8)
Requires-Dist: google-cloud-datastore (~=2.3)
Requires-Dist: google-auth (~=2.3)
